torchskradon/__init__.py
torchskradon/functional.py
torchskradon/helpers.py
torchskradon-0.1.1.dist-info/licenses/LICENSE
torchskradon-0.1.1.dist-info/METADATA
torchskradon-0.1.1.dist-info/WHEEL
torchskradon-0.1.1.dist-info/top_level.txt
torchskradon-0.1.1.dist-info/RECORD
