Metadata-Version: 2.4
Name: torchskradon
Version: 0.1.1
Summary: A differentiable implementation of scikit-image's Radon transform and filtered backprojection in PyTorch
Author-email: Tom Lütjen <tom.luetjen@icloud.com>
License: MIT
Project-URL: Repository, https://github.com/tomluetjen/torchskradon.git
Project-URL: Issues, https://github.com/tomluetjen/torchskradon/issues
Keywords: pytorch,skimage,radon,tomography
Classifier: Development Status :: 4 - Beta
Classifier: Intended Audience :: Developers
Classifier: License :: OSI Approved :: MIT License
Classifier: Programming Language :: Python :: 3 :: Only
Classifier: Programming Language :: Python :: 3.10
Classifier: Programming Language :: Python :: 3.11
Classifier: Programming Language :: Python :: 3.12
Classifier: Topic :: Scientific/Engineering :: Artificial Intelligence
Requires-Python: >=3.10
License-File: LICENSE
Requires-Dist: torch>=2.2
Provides-Extra: tests
Requires-Dist: torchvision>=0.17; extra == "tests"
Requires-Dist: ruff>=0.6.9; extra == "tests"
Requires-Dist: scikit-image>=0.22; extra == "tests"
Requires-Dist: matplotlib>=3.8; extra == "tests"
Requires-Dist: pytest>=8.2; extra == "tests"
Requires-Dist: pytest-benchmark>=4.0; extra == "tests"
Requires-Dist: pytest-cov>=5.0; extra == "tests"
Provides-Extra: dev
Requires-Dist: torchvision>=0.17; extra == "dev"
Requires-Dist: ruff>=0.6.9; extra == "dev"
Requires-Dist: scikit-image>=0.22; extra == "dev"
Requires-Dist: matplotlib>=3.8; extra == "dev"
Requires-Dist: pytest>=8.2; extra == "dev"
Requires-Dist: pytest-benchmark>=4.0; extra == "dev"
Requires-Dist: pytest-cov>=5.0; extra == "dev"
Dynamic: license-file
